Metadata-Version: 2.1
Name: itchat-uos-patch
Version: 1.6.0
Summary: A complete wechat personal account api
Home-page: https://github.com/teg1c/ItChat-UOS
Author: tegic
Author-email: teg1c@foxmail.com
License: MIT
Keywords: wechat itchat api robot weixin personal extend
Platform: UNKNOWN
Classifier: Development Status :: 3 - Alpha
Classifier: Intended Audience :: Developers
Classifier: Topic :: Software Development :: Libraries :: Python Modules
Classifier: License :: OSI Approved :: MIT License
Classifier: Programming Language :: Python :: 2
Classifier: Programming Language :: Python :: 2.6
Classifier: Programming Language :: Python :: 2.7
Classifier: Programming Language :: Python :: 3.5
Classifier: Programming Language :: Python :: 3.6
Classifier: Programming Language :: Python :: 3.7
Classifier: Programming Language :: Python :: 3.8
Classifier: Programming Language :: Python :: 3.9
License-File: LICENSE
Requires-Dist: requests
Requires-Dist: pyqrcode
Requires-Dist: pypng
